{
  "name": "Requestly",

  "version": "4.1.4",
  "manifest_version": 2,
  "description": "Chrome Extension to modify HTTP requests (Redirect | Cancel | Replace | Modify Headers)",

  "content_scripts": [
    {
      "matches": [ "*://web.requestly.in/*" ],
      "css": [ "src/pages/main.css" ],
      "js": [ "src/pages/libs.js", "src/pages/main.js" ]
    }
  ],

  "background": {
    "scripts": [
      "browser_config.js",
      "src/background/storageService.js",
      "src/Shared/shared.js",
      "src/Shared/utils.js",
      "src/background/background.js"
    ]
  },

  "applications": {
    "gecko": {
      "id": "requestly@mozilla.org",
      "strict_min_version": "48.0.0"
    }
  },

  "content_security_policy": "script-src 'self' 'unsafe-eval' https://cdn.firebase.com https://*.firebaseio.com; object-src 'self'",

  "browser_action": {
    "default_icon": "resources/images/128x128.png",
    "default_title": "Modify HTTP/HTTPS requests"
  },

  "icons": {
    "16": "resources/images/19x19.png",
    "128": "resources/images/128x128.png"
  },
  
  "permissions": [
    "contextMenus",
    "storage",
    "webRequest",
    "webRequestBlocking",
    "tabs",
    "http://*/*",
    "https://*/*"
  ]
}
